iflow_mcp_semantic_scholar_fastmcp_mcp_server-0.1.0.dist-info/licenses/LICENSE
semantic_scholar/__init__.py
semantic_scholar/config.py
semantic_scholar/mcp.py
semantic_scholar/server.py
semantic_scholar/api/__init__.py
semantic_scholar/api/authors.py
semantic_scholar/api/papers.py
semantic_scholar/api/recommendations.py
semantic_scholar/utils/__init__.py
semantic_scholar/utils/errors.py
semantic_scholar/utils/http.py
iflow_mcp_semantic_scholar_fastmcp_mcp_server-0.1.0.dist-info/METADATA
iflow_mcp_semantic_scholar_fastmcp_mcp_server-0.1.0.dist-info/WHEEL
iflow_mcp_semantic_scholar_fastmcp_mcp_server-0.1.0.dist-info/entry_points.txt
iflow_mcp_semantic_scholar_fastmcp_mcp_server-0.1.0.dist-info/top_level.txt
iflow_mcp_semantic_scholar_fastmcp_mcp_server-0.1.0.dist-info/RECORD
