Metadata-Version: 2.4
Name: iflow-mcp_semantic-scholar-fastmcp-mcp-server
Version: 0.1.0
Summary: A FastMCP server implementation for the Semantic Scholar API
Author-email: IFLOW <iflow@example.com>
License: MIT
Requires-Python: >=3.8
License-File: LICENSE
Requires-Dist: httpx>=0.24.0
Requires-Dist: python-dotenv>=1.0.0
Requires-Dist: uvicorn>=0.27.1
Requires-Dist: fastmcp>=0.1.0
Provides-Extra: dev
Requires-Dist: pytest>=7.3.1; extra == "dev"
Requires-Dist: pytest-asyncio>=0.21.0; extra == "dev"
Dynamic: license-file
